[
  {
    "id": "cmisv99xs000j04i65o5rdm2a",
    "title": "Dotto v1.5.3 がリリースされました",
    "date": "2025-12-06T12:00:00+09:00",
    "url": "https://fun-dotto.github.io/releases/v1.5.3",
    "is_active": true
  },
  {
    "id": "cmii7btln000004js2ucl7unr",
    "title": "Dotto v1.5.2 がリリースされました",
    "date": "2025-11-28T12:00:00+09:00",
    "url": "https://fun-dotto.github.io/releases/v1.5.2",
    "is_active": true
  },
  {
    "id": "cmi6zt7p1000004ju3egn77nf",
    "title": "Dotto v1.5.1 がリリースされました",
    "date": "2025-11-22T12:00:00+09:00",
    "url": "https://fun-dotto.github.io/releases/v1.5.1",
    "is_active": true
  },
  {
    "id": "i613ud8jqeng0uu0xl3dkqa5",
    "title": "未来祭 2025 に出店します！",
    "date": "2025-10-11T10:00:00+09:00",
    "url": "https://fun-dotto.github.io/articles/miraisai2025",
    "is_active": true
  },
  {
    "id": "cmghdpo55000104jx37njhrnt",
    "title": "Dotto v1.5.0 がリリースされました",
    "date": "2025-10-09T00:00:00+09:00",
    "url": "https://fun-dotto.github.io/releases/v1.5.0",
    "is_active": true
  },
  {
    "id": "eg77bs8o0ngxovjwwhwtin7u",
    "title": "函館バス令和 7 年度冬期ダイヤ改正に伴うデータ更新について",
    "date": "2025-10-03T21:30:00+09:00",
    "url": "https://fun-dotto.github.io/articles/hakodatebus_timetable_revision_2510",
    "is_active": true
  },
  {
    "id": "qawuistatvy4yieyhrrv0tei",
    "title": "Dotto v1.4.1 がリリースされました",
    "date": "2025-07-10T00:00:00+09:00",
    "url": "https://fun-dotto.github.io/releases/v1.4.1",
    "is_active": true
  },
  {
    "id": "c0idm2awgxw9ju242nt4h14p",
    "title": "Dotto v1.4.0 がリリースされました",
    "date": "2025-03-31T00:00:00+09:00",
    "url": "https://fun-dotto.github.io/releases/v1.4.0",
    "is_active": true
  },
  {
    "id": "vpfkusm2ilvenisqxf7y9oi9",
    "title": "Dotto v1.3.1 がリリースされました",
    "date": "2025-01-31T00:00:00+09:00",
    "url": "https://fun-dotto.github.io/releases/v1.3.1",
    "is_active": true
  },
  {
    "id": "wzk2fe1zwfyf1jxal0okft2x",
    "title": "Dotto v1.3.0 がリリースされました",
    "date": "2025-01-28T00:00:00+09:00",
    "url": "https://fun-dotto.github.io/releases/v1.3.0",
    "is_active": true
  },
  {
    "id": "ib4jks839r0jnv2k45nuu78a",
    "title": "Dotto v1.2.2 がリリースされました",
    "date": "2024-11-08T12:00:00+09:00",
    "url": "https://fun-dotto.github.io/releases/v1.2.2",
    "is_active": true
  },
  {
    "id": "q7fwpht6eipkyk6t4nyasp86",
    "title": "未来祭2024に出店します！",
    "date": "2024-10-08T15:25:00+09:00",
    "url": "https://fun-dotto.github.io/articles/miraisai2024",
    "is_active": false
  }
]
